Workbook

Sheet Servidores
A1: Cuadro Comparativo de Cotizaciones
A4: Cotización | B4: Tipo de Servidor | C4: Proveedor | D4: Descripcion | E4: Valor Total | F4: Forma de Pago | G4: Obsevaciones
A5: COT-001 | B5: Local | C5: Dell Technologies | D5: Servidor Dell PowerEdge T40 Intel Xeon E-2224G, 8GB RAM, 1TB HDD | E5: $ 4200000 | F5: Contado | G5: https://tiendalenovomedellin.com/products/servidor-dell-poweredge-t40-xeon-e3-2224g?srsltid=AfmBOopmMFn7a-tb0M4POwNjXI27LKDzUBUrvznDq6uxzHfdGVEBsdXX&utm_source=chatgpt.com
A6: COT-003 | B6: Local | C6: Lenovo | D6: ThinkSystem ST50 V2, Xeon E-2324G, 16GB RAM, 2TB HDD | E6: $ 4571429 | F6: Contado | G6: https://systorecolombia.com/torre/389-servidor-lenovo-st50-v2-xeon-e2324g-16gb-2tb-7d8ka00ala.html

Sheet Equipos de computo
A1: Cuadro Comparativo de Cotizaciones
A4: Cotización | B4: Proveedor | C4: Descripcion | D4: Modulo | E4: Valor Total | F4: Forma de Pago | G4: Estado | H4: Obsevaciones | I4: URLS
A5: N°1 | B5: Alkosto | C5: Computador All In One LENOVO IdeaCentre AIO | D5: Administrador | E5: 3999070 | F5: contado | G5: NUEVO | H5: 27" Pulgadas 27IRH9 - Intel Core i7 - RAM 16GB - Disco SSD 512GB - Gris | I5: https://www.alkosto.com/computador-all-in-one-lenovo-ideacentre-aio-27-pulgadas/p/198153841134
A6: N°2 | B6: Alkosto | C6: Computador All In One LENOVO IdeaCentre AIO | D6: Optometra | E6: 2199070 | F6: contado | G6: NUEVO | H6: 27" Pulgadas 27IRH9 - Intel Core i5 - RAM 8GB - Disco SSD 512GB - Gris | I6: https://www.alkosto.com/computador-all-in-one-lenovo-ideacentre-aio-27-pulgadas/p/198155085390
A7: N°3 | B7: Mercado Libre | C7: Portatil Asus Vivobook | D7: Empleado(Bodega) | E7: 1299000 | F7: contado | G7: NUEVO | H7: E1504ga Core I3 N305 Ram 8gb 512gb Color Gris | I7: https://www.mercadolibre.com.co/portatil-asus-vivobook-e1504ga-core-i3-n305-ram-8gb-512gb-color-gris/p/MCO51203431#polycard_client=search-nordic&search_layout=stack&position=3&type=product&tracking_id=fd9a58a6-78d1-4232-98d0-5133b59c83a0&wid=MCO2953509182&sid=search
A8: N°4 | B8: Alkosto | C8: Computador All In One LENOVO | D8: Empleado(Caja) | E8: 1799070 | F8: contado | G8: NUEVO | H8: 23.8" Pulgadas A100 - Intel Core i3 - RAM 8GB - Disco SSD 512GB - Gris | I8: https://www.alkosto.com/computador-all-in-one-lenovo-238-pulgadas-a100-intel-core/p/198156629623
A9: N°5 | B9: Mercado Libre | C9: Portatil Asus Vivobook | D9: Empleado (Proveedor) | E9: 1299000 | F9: contado | G9: NUEVO | H9: E1504ga Core I3 N305 Ram 8gb 512gb Color Gris | I9: https://www.mercadolibre.com.co/portatil-asus-vivobook-e1504ga-core-i3-n305-ram-8gb-512gb-color-gris/p/MCO51203431#polycard_client=search-nordic&search_layout=stack&position=3&type=product&tracking_id=fd9a58a6-78d1-4232-98d0-5133b59c83a0&wid=MCO2953509182&sid=search
A10: N°6 | B10: Mercado Libre | C10: Portatil Lenovo V14 | D10: Lider de Proyecto | E10: 1799900 | F10: contado | G10: NUEVO | H10: 14" Pulgadas core i5 13420H-S.OWindows-SSD:512 GB-24 GB RAM-color Negro. | I10: https://www.mercadolibre.com.co/portatil-lenovo-v14-core-i5-13420h-24gb-512gb-ssd-color-negro/p/MCO44279796?product_trigger_id=MCO44291281&picker=true
A11: N°7 | B11: Katronix | C11: Computador Portátil HP ProBook | D11: Desarrollador Frontend | E11: 5809030 | F11: contado | G11: NUEVO | H11: 15.6" Pulgadas PB450 G10 - Intel Core i7 - RAM 16GB - Disco SSD 1 TB - Plateado | I11: https://www.ktronix.com/computador-portatil-hp-probook-156-pulgadas-pb450-g10/p/198828758040
A12: N°8 | B12: Katronix | C12: Computador Portátil HP ProBook | D12: Desarrollador Backend | E12: 5809030 | F12: contado | G12: NUEVO | H12: 15.6" Pulgadas PB450 G10 - Intel Core i7 - RAM 16GB - Disco SSD 1 TB - Plateado | I12: https://www.ktronix.com/computador-portatil-hp-probook-156-pulgadas-pb450-g10/p/198828758040
A13: N°9 | B13: Mercado Libre | C13: Portatil Lenovo V14 | D13: Analista QA/Testing | E13: 1799900 | F13: contado | G13: NUEVO | H13: 14" Pulgadas core i5 13420H-S.OWindows-SSD:512 GB-24 GB RAM-color Negro. | I13: https://www.mercadolibre.com.co/portatil-lenovo-v14-core-i5-13420h-24gb-512gb-ssd-color-negro/p/MCO44279796?product_trigger_id=MCO44291281&picker=true

Sheet Dominio
A1: Cuadro Comparativo de Cotizaciones
A4: Cotización | B4: Proveedor | C4: URL (Datos de la empresa ) | D4: Descripcion | E4: Valor Total | F4: IVA Incluido | G4: Valor Total2 | H4: Forma de Pago | I4: Obsevaciones
A5: N°1 | B5: Colombia Hosting | C5: https://www.colombiahosting.com.co/registro-dominios#transfer | D5: .com | E5: 57000 | F5: =Tabla36[[#This Row],[Valor Total]]*19% -> 10830 | G5: =Tabla36[[#This Row],[Valor Total]]+Tabla36[[#This Row],[IVA Incluido]] -> 67830 | H5: contado | I5: La extensión más reconocida y confiable mundialmente. Atrae a más visitantes y proyecta una imagen profesional para tu sitio web.
A6: N°2 | B6: HOSTINGER | C6: https://www.hostinger.com/co/comprar-dominio?utm_campaign=Generic-Domains|NT:Se|LO:CO&utm_medium=ppc&gad_source=1&gad_campaignid=10835301752&gbraid=0AAAAADMy-hbjhmU6MB-zZ24oX4lYvKZP0&gclid=EAIaIQobChMI-t2BkP_-kAMVd4VaBR2_Uj0ZEAAYAiAAEgJHFvD_BwE | D6: .com | E6: 58900 | F6: =Tabla36[[#This Row],[Valor Total]]*19% -> 11191 | G6: =Tabla36[[#This Row],[Valor Total]]+Tabla36[[#This Row],[IVA Incluido]] -> 70091 | H6: contado | I6: Inspira confianza con este dominio reconocido.
A7: N°3 | B7: HostGator | C7: https://www.hostgator.co/dominios | D7: .com | E7: =(30800)/0.59 -> 52203.39 | F7: =Tabla36[[#This Row],[Valor Total]]*19% -> 9918.6441 | G7: =Tabla36[[#This Row],[Valor Total]]+Tabla36[[#This Row],[IVA Incluido]] -> 62122.034 | H7: contado | I7: Obten relevencia internacional para tu marca.
A8: N°4 | B8: Mi.com.co | C8: https://mi.com.co/Dominios | D8: .com | E8: 59900 | F8: =Tabla36[[#This Row],[Valor Total]]*19% -> 11381 | G8: =Tabla36[[#This Row],[Valor Total]]+Tabla36[[#This Row],[IVA Incluido]] -> 71281 | H8: contado | I8: Es uno de los más importantes y reconocidos a nivel mundial
F9: =Tabla36[[#This Row],[Valor Total]]*19% -> 0 | G9: =Tabla36[[#This Row],[Valor Total]]+Tabla36[[#This Row],[IVA Incluido]] -> 0
F10: =Tabla36[[#This Row],[Valor Total]]*19% -> 0 | G10: =Tabla36[[#This Row],[Valor Total]]+Tabla36[[#This Row],[IVA Incluido]] -> 0

Sheet Licencias Microsoft
A1: Cuadro Comparativo de Cotizaciones
A4: Cotización | B4: Proveedor | C4: Descripcion | D4: Valor Total | E4: Observaciones | F4: Obsevaciones
A5: COT-001 | B5: SYSCARIBE | C5: Microsoft 365 Empresa Premium (Suscripción 1 Año) | D5: 1150000 | E5: Administración de identidad y acceso avanzada Protección mejorada frente a ciberamenazas contra virus y ataques de phishing Protección de dispositivos y puntos de conexión de grado empresarial Descubre, clasifica y protege información confidencial Microsoft 365 Copilot está disponible como complemento | F5: https://www.syscaribe.com/producto/microsoft-365-business-premium-suscripcion-1-ano/
A6: COT-002 | B6: MICROSOFT | C6: Microsoft 365 Empresa Básico | D6: 2247378 | E6: Administración de identidad y acceso para hasta 300 usuarios Versiones web y móviles3 de Word, Excel, PowerPoint y Outlook Correo empresarial personalizado (nombre@tu empresa.com) Chat, llamadas y videoconferencias con Microsoft Teams 1 TB de almacenamiento en la nube por usuario Más de 10 aplicaciones adicionales para tus necesidades empresariales (incluidas Microsoft Bookings, Planner y Forms) Experiencia de chat con tecnología de IA con base web, asistencia en redacción, análisis de datos y acceso a agentes4 Filtrado automático de correo no deseado y malware Soporte ininterrumpido por teléfono y a través de la Web | F6: https://www.microsoft.com/es-co/microsoft-365/business/microsoft-365-plans-and-pricing
A7: COT-003

Sheet Hosting-Servidor-web
A1: Cuadro Comparativo de Cotizaciones
A4: Cotización | B4: Proveedor | C4: URL (Datos de la empresa) | D4: Descripcion | E4: Valor Total | F4: IVA Incluido | G4: Valor Total2 | H4: Forma de Pago | I4: Obsevaciones
A5: N°1 | B5: Mi.com.co | C5: https://mi.com.co/hosting | D5: Hosting Advanced (5 GB- 9GB) | E5: 169900 | F5: =Tabla367[[#This Row],[Valor Total]]*19% -> 32281 | G5: =Tabla367[[#This Row],[Valor Total]] + Tabla367[[#This Row],[IVA Incluido]] -> 202181 | H5: contado | I5: * Almacenamiento SSD NVMe: 9GB * SSL gratis para todos tus dominios * 2GB de memoria RAM * 10 sitios web y subdominios *Redirecciona 10 dominios * 20 bases de datos *Tráfico ilimitado * Migración gratis *WordPress, Joomla y más * Copias de seguridad mensuales *Sistema operativo CloudLinux * PHP, Node.js, Python, Ruby * Seguridad avanzada Imunify360 * Hasta 2 millones de archivos
A6: N°2 | B6: Latinoamerica hosting | C6: https://www.latinoamericahosting.com.co/hosting/?gad_source=1&gad_campaignid=11605730357&gbraid=0AAAAAByL0_gt1n038ZNZe-XNHYLyWOpts&gclid=EAIaIQobChMIj_6F94r_kAMVtadaBR0s9jQPEAAYASAAEgJug_D_BwE | D6: Hosting H2 (30 GB) | E6: 170000 | F6: =Tabla367[[#This Row],[Valor Total]]*19% -> 32300 | G6: =Tabla367[[#This Row],[Valor Total]] + Tabla367[[#This Row],[IVA Incluido]] -> 202300 | H6: contado | I6: *30 GB Espacio SSD NVMe *600 GB de Tráfico / mes *2 CPU / Garantizado *4 GB de memoria RAM * IPv4 + IPv6 activado *20 Cuentas E-mail *5 Bases de datos *2 Dominios permitidos *WordPress / Joomla / Otros *LiteSpeed + LSCache * Seguridad Imunify360 *Constructor de sitios Pro * Copias de seguridad * SSL gratis (https://)
A7: N°3 | B7: bluehosting | C7: https://www.bluehosting.com.co/ | D7: Hosting full (ilimitado) | E7: 210000 | F7: =Tabla367[[#This Row],[Valor Total]]*19% -> 39900 | G7: =Tabla367[[#This Row],[Valor Total]] + Tabla367[[#This Row],[IVA Incluido]] -> 249900 | H7: contado | I7: * 40% más poderoso que plan * Emprendedores Power *Espacio almacenamiento SSD Ilimitado *Sitios web ilimitados *Cuentas de correo ilimitadas * 4 GB de memoria RAM *Transferencia de datos sin medición *Base de datos ilimitado *Transferencia de datos ilimitado *SSL Gratuito Let’s Encrypt ilimitado
A8: N°4 | B8: Colombia Hosting | C8: https://www.colombiahosting.com.co/hosting | D8: Hosting Colhost 2 (20 GB) | E8: 432000 | F8: =Tabla367[[#This Row],[Valor Total]]*19% -> 82080 | G8: =Tabla367[[#This Row],[Valor Total]] + Tabla367[[#This Row],[IVA Incluido]] -> 514080 | H8: contado | I8: *2 web *20 bases de datos *20 GB NVMe SSD *20 cuentas de correo *Creador de sitios web *2 Certificado SSL *Email Marketing
F9: =Tabla367[[#This Row],[Valor Total]]*19% -> 0 | G9: =Tabla367[[#This Row],[Valor Total]] + Tabla367[[#This Row],[IVA Incluido]] -> 0
F10: =Tabla367[[#This Row],[Valor Total]]*19% -> 0 | G10: =Tabla367[[#This Row],[Valor Total]] + Tabla367[[#This Row],[IVA Incluido]] -> 0
F11: =Tabla367[[#This Row],[Valor Total]]*19% -> 0 | G11: =Tabla367[[#This Row],[Valor Total]] + Tabla367[[#This Row],[IVA Incluido]] -> 0

Sheet Licencias de Windows
A1: Cuadro Comparativo de Cotizaciones
A4: Cotización | B4: Proveedor | C4: URL (Datos de la empresa) | D4: Descripcion | E4: Valor Total | F4: IVA Incluido | G4: Valor Total2 | H4: Forma de Pago | I4: Obsevaciones
A5: N°1 | B5: Buho Digital | C5: https://buhodigitalcol.com/licencia-windows-11-pro/?srsltid=AfmBOoosj4MAWsyyDo9CcP1SesAbr_09Ga2x1xZZAqndC0GxetbvgJz3sBg | D5: Windows 11 pro | E5: 99900 | F5: =Tabla36789[[#This Row],[Valor Total]] * 19% -> 18981 | G5: =Tabla36789[[#This Row],[Valor Total]] + Tabla36789[[#This Row],[IVA Incluido]] -> 118881 | H5: Contado | I5: Esta licencia Windows 11 es compatible con la versión Windows 11 Professional, es una licencia totalmente legitima, legal y sirve para activar Windows 11 pro en un computador una sola vez, en caso de formateo es posible reinstalarla siempre y cuando sea el mismo equipo y no se hayan hecho cambios significativos de hardware. (realizar este proceso bajo su responsabilidad) Ideal para entornos empresariales y de hogar, aplica para auditorias empresariales.
A6: N°2 | B6: Tulicencia | C6: https://tulicencias.com/product/windows-11-pro/?currency=COP&srsltid=AfmBOooFL0vqHP1Vf4LOoTxFJ8Vap6vXkePu7CMm2jAfip2uDJcHj8Z_d3s | D6: Windows 11 pro | E6: 39900 | F6: =Tabla36789[[#This Row],[Valor Total]] * 19% -> 7581 | G6: =Tabla36789[[#This Row],[Valor Total]] + Tabla36789[[#This Row],[IVA Incluido]] -> 47481 | H6: Contado | I6: * Activación en línea *Licencia de por vida para 1 PC *Clave original de 25 caracteres * Licencia vinculada a su cuenta Microsoft * Puede reinstalarla en el mismo PC * Permite instalación limpia o reinstalación de Windows *Posible actualización de Windows Home / Home Single Language a Windows Pro (se envía manual) *Envío instantáneo por correo electrónico *Disponible en todos los idiomas
A7: N°3 | B7: Olimpica | C7: https://www.olimpica.com/windows-11-pro-1-dispositivo-1002383543/p?idsku=1100208090 | D7: Windows 11 pro | E7: 116900 | F7: =Tabla36789[[#This Row],[Valor Total]] * 19% -> 22211 | G7: =Tabla36789[[#This Row],[Valor Total]] + Tabla36789[[#This Row],[IVA Incluido]] -> 139111 | H7: Contado | I7: *SEGURIDAD AVANZADA Protección integral con antiphishing y cortafuegos, defendiendo tus dispositivos contra amenazas en tiempo real. *MEJORA DE RENDIMIENTO Herramientas de limpieza y gestión de aplicaciones para optimizar la velocidad y eficiencia de tus dispositivos. *PROTECCIÓN DE PAGOS EN LÍNEA Garantiza transacciones seguras y protege tu información financiera al comprar por Internet. *COMPATIBILIDAD MULTIPLATAFORMA Disponible para Windows®, macOS®, Android™ e iOS®, ofreciendo cobertura para todos tus dispositivos. *CIBERSEGURIDAD PREMIADA Una solución confiable y galardonada, diseñada para mantener tus datos protegidos de amenazas en línea
A8: N°4 | B8: Exito | C8: https://www.exito.com/windows-11-pro-retail-102325516-mp/p | D8: Windows 11 pro | E8: 99000 | F8: =Tabla36789[[#This Row],[Valor Total]] * 19% -> 18810 | G8: =Tabla36789[[#This Row],[Valor Total]] + Tabla36789[[#This Row],[IVA Incluido]] -> 117810 | H8: Contado | I8: *Tipo de licencia: Las licencias de fabricante original OEM (Original Equipment Manufacturer) son un tipo de licencia que los desarrolladores de software suministran a los fabricantes de hardware para que las utilicen en el ensamblaje de sus propios productos. *Apto para: Hogar y Empresas *Cuantos Pc : 1 Pc *Reinstalable: SI *Trasferible: NO *Funciona para: Windows *Activacion: 100 % Activacion por Internet *Duracion: Licencia vitalicia no vence
F9: =Tabla36789[[#This Row],[Valor Total]] * 19% -> 0 | G9: =Tabla36789[[#This Row],[Valor Total]] + Tabla36789[[#This Row],[IVA Incluido]] -> 0
F10: =Tabla36789[[#This Row],[Valor Total]] * 19% -> 0 | G10: =Tabla36789[[#This Row],[Valor Total]] + Tabla36789[[#This Row],[IVA Incluido]] -> 0
F11: =Tabla36789[[#This Row],[Valor Total]] * 19% -> 0 | G11: =Tabla36789[[#This Row],[Valor Total]] + Tabla36789[[#This Row],[IVA Incluido]] -> 0

Sheet Visual Studio
A1: Cuadro Comparativo de Cotizaciones
A4: Cotización | B4: Proveedor | C4: URL (Datos de la empresa) | D4: Descripcion | E4: Valor Total | F4: IVA Incluido | G4: Valor Total2 | H4: Forma de Pago | I4: Obsevaciones
A5: Nº1 | B5: Revolution Soft Colombia | C5: http://revolutionsoft.com.co/programacion/microsoft-visual-studio-2022-professional.html | D5: Visual Studio Profesional(2019) | E5: 99000 | F5: =Tabla3678910[[#This Row],[Valor Total]]*19% -> 18810 | G5: =Tabla3678910[[#This Row],[Valor Total]] + Tabla3678910[[#This Row],[IVA Incluido]] -> 117810 | H5: Contado | I5: *Compatibilidad con múltiples lenguajes de programación, incluyendo C#, C++, Python, JavaScript, TypeScript, F# y más. *IntelliCode con inteligencia artificial, mejorando la productividad con sugerencias automáticas. * Herramientas avanzadas de depuración y pruebas, facilitando la detección y solución de errores. * Integración con Git y Azure DevOps, permitiendo colaboración en equipos y control de versiones eficiente. *Compatibilidad con .NET 6 y .NET MAUI, optimizando el desarrollo de aplicaciones multiplataforma. *Soporte para desarrollo de aplicaciones web, móviles, de escritorio y en la nube. * Análisis de código y refactorización automatizada, mejorando la calidad del código. *Compatibilidad con contenedores y Kubernetes, facilitando el desarrollo en entornos Docker.
A6: Nº2 | B6: G2A | C6: http://g2a.com/es/microsoft-visual-studio-2022-enterprise-pc-microsoft-key-global-i10000325952001?___language=es&er=3cf501fcfc436491a2261e5494f1762b3db45ff7b5ae84696b3ada99c163e4856bd1e617e82e2ae014844d8920b833fd&uuid=ab06a8fa-cb54-4101-9de2-7ea433024223&srsltid=AfmBOoqgpuaT5WnkXrAKXR6CqQpRTYA_oBAGb1CeMO54gEfv44_1NccTsE0 | D6: Visual Studio Profesional(2022) | E6: 134900 | F6: =Tabla3678910[[#This Row],[Valor Total]]*19% -> 25631 | G6: =Tabla3678910[[#This Row],[Valor Total]] + Tabla3678910[[#This Row],[IVA Incluido]] -> 160531 | H6: Contado | I6: *Productivo: escala para trabajar en proyectos de cualquier tamaño y complejidad con un IDE de 64 bits. Codifica con un nuevo editor Razor que puede refactorizar entre archivos. Diagnostica problemas con visualizaciones para operaciones asíncronas y analizadores automáticos. *Moderno: desarrolla aplicaciones móviles y de escritorio multiplataforma con .NET MAUI. Crea interfaces de usuario web responsivas en C# con Blazor. Crea, depura y prueba aplicaciones .NET y C++ en entornos Linux. Usa las capacidades de recarga en caliente en aplicaciones .NET y C++. Edita páginas ASP.NET en ejecución en la vista del diseñador web *Innovador: autocompletado de código impulsado por IA. Colabore en tiempo real con sesiones de codificación compartidas. Clone repositorios, navegue por elementos de trabajo y prepare líneas individuales para confirmaciones. Configure automáticamente flujos de trabajo de CI/CD que se pueden implementar en Azure.
A7: Nº3 | B7: 3clics | C7: https://3clics.co/index.php/es/otros-softwares/editor-de-codigo/licencia-visual-studio-2022-detail | D7: Visual Studio Profesional(2022) | E7: 117850 | F7: =Tabla3678910[[#This Row],[Valor Total]]*19% -> 22391.5 | G7: =Tabla3678910[[#This Row],[Valor Total]] + Tabla3678910[[#This Row],[IVA Incluido]] -> 140241.5 | H7: Contado | I7: Visual Studio es uno de los editores de código más populares en el mundo. Esta licencia activa la versión "Pro" que desbloquea todas las características del Software. Visual Studio 2022, como una aplicación de 64 bits, ofrece un rendimiento y escalabilidad superiores a Visual Studio 2019, mejorando la gestión de proyectos grandes y la utilización de memoria. Incluye una interfaz de usuario más moderna, mejor soporte para las últimas tecnologías y lenguajes, herramientas de depuración avanzadas, integración mejorada con Git y GitHub, y capacidades avanzadas de IntelliCode basadas en inteligencia artificial. Además, proporciona mejores herramientas para la colaboración en equipo y el desarrollo remoto, haciéndolo más adecuado para proyectos modernos y complejos.
A8: Nº4 | B8: Mr. Licencias | C8: https://mrlicencias.com/products/visual-studio-2019-professional?_pos=3&_sid=d22f32169&_ss=r&variant=41274197049522&srsltid=AfmBOooblmN0PYcCKhAYsNhJFWYG6aZlXDNV2M2H2aFvASDCFuG2UidnxHM | D8: Visual Studio Profesional(2019) | E8: 298650 | F8: =Tabla3678910[[#This Row],[Valor Total]]*19% -> 56743.5 | G8: =Tabla3678910[[#This Row],[Valor Total]] + Tabla3678910[[#This Row],[IVA Incluido]] -> 355393.5 | H8: Contado | I8: Visual Studio permite a los desarrolladores crear sitios y aplicaciones web, así como servicios web en cualquier entorno compatible con la plataforma .NET. Así, se pueden crear aplicaciones que se comuniquen entre estaciones de trabajo, páginas web, dispositivos móviles, videoconsolas, entre otros.

Sheet Base de Datos
A1: Cuadro Comparativo de Cotizaciones
A4: Cotización | B4: Proveedor | C4: URL (Datos de la empresa) | D4: Descripcion | E4: Valor Total | F4: IVA Incluido | G4: Valor Total2 | H4: Forma de Pago | I4: Obsevaciones
A5: Nº1 | B5: Revolution Soft Colombia | C5: https://revolutionsoft.com.co/windows-server/sql-server-2022-standard.html | D5: Microsoft SQL Standart Edition (24 cores-usuarios ilimitados) | E5: 1790000 | F5: =Tabla367891011[[#This Row],[Valor Total]]*19% -> 340100 | G5: =Tabla367891011[[#This Row],[Valor Total]]+Tabla367891011[[#This Row],[IVA Incluido]] -> 2130100 | H5: Contado | I5: *Soporte para hasta 24 cores físicos, optimizando el rendimiento de grandes cargas de trabajo. * Usuarios ilimitados, permitiendo múltiples conexiones simultáneas sin restricciones. * Mejora en la consulta de bases de datos, con optimización inteligente de rendimiento. * Soporte para integración en la nube con Azure, facilitando la conectividad híbrida. * Alta disponibilidad y recuperación ante desastres, con Always On Failover Clusters. *Mayor seguridad con cifrado de datos, auditoría avanzada y protección contra amenazas. * Compatibilidad con Big Data Clusters, permitiendo análisis de datos en entornos empresariales
A6: Nº2 | B6: Ebay | C6: https://www.ebay.com/itm/145519556112?chn=ps&mkevt=1&mkcid=28&google_free_listing_action=view_item | D6: Microsoft SQL Standart Edition (24 cores-usuarios ilimitados) | E6: 4806700 | F6: =Tabla367891011[[#This Row],[Valor Total]]*19% -> 913273 | G6: =Tabla367891011[[#This Row],[Valor Total]]+Tabla367891011[[#This Row],[IVA Incluido]] -> 5719973 | H6: Contado | I6: SQL Server 2022 introduce una nueva integración de almacenamiento de objetos en la plataforma de datos, lo que te permite integrar SQL Server con almacenamiento de objetos compatible con S3, además de Azure Storage. La primera es una copia de seguridad en URL y la segunda es Data Lake Virtualization Microsoft Defender para la integración en la nube Protege tus servidores SQL con el plan Defender for SQL. El plan Defender for SQL requiere que SQL Server Extension for Azure esté habilitado e incluye funcionalidades para descubrir y mitigar posibles vulnerabilidades de bases de datos y detectar actividades anómalas que podrían indicar una amenaza para tus bases de datos. Obtén más información sobre cómo Defender for SQL puede proteger todo el estado de tu base de datos en cualquier lugar: entornos locales, híbridos y multinube.
A7: Nº3 | B7: ELENST | C7: https://www.elenst.com/p/microsoft-sql-server-2022-standard/ | D7: Microsoft SQL Standart Edition | E7: 2342259 | F7: =Tabla367891011[[#This Row],[Valor Total]]*19% -> 445029.21 | G7: =Tabla367891011[[#This Row],[Valor Total]]+Tabla367891011[[#This Row],[IVA Incluido]] -> 2787288.2 | H7: Contado | I7: SQL Server 2022 permite a los administradores de bases de datos y a los equipos de TI gestionar sus activos de datos de forma más eficiente, con mayor flexibilidad y mínimo impacto en los usuarios finales. Es una solución ideal para organizaciones que requieren una plataforma robusta, inteligente y preparada para el futuro de la nube híbrida y la analítica avanzada.
A8: Nº4 | B8: La Tienda de las Licencias | C8: https://latiendadelaslicencias.com/es/microsoft-sql-server/sql-server-2022-standard.html?utm_source=chatgpt.com | D8: Microsoft SQL Standart Edition (24 cores-usuarios ilimitados) | E8: 3907000 | F8: =Tabla367891011[[#This Row],[Valor Total]]*19% -> 742330 | G8: =Tabla367891011[[#This Row],[Valor Total]]+Tabla367891011[[#This Row],[IVA Incluido]] -> 4649330 | H8: Contado | I8: Microsoft SQL Server 2022 Standard es la última versión del popular sistema de gestión de bases de datos relacionales de Microsoft, actualizado con las últimas funciones y características para el manejo de datos. Esta licencia específica es para la edición Standard y cubre hasta 24 núcleos, lo que significa que puede ser utilizada en un servidor con hasta 24 núcleos de procesado
F9: =Tabla367891011[[#This Row],[Valor Total]]*19% -> 0 | G9: =Tabla367891011[[#This Row],[Valor Total]]+Tabla367891011[[#This Row],[IVA Incluido]] -> 0
F10: =Tabla367891011[[#This Row],[Valor Total]]*19% -> 0 | G10: =Tabla367891011[[#This Row],[Valor Total]]+Tabla367891011[[#This Row],[IVA Incluido]] -> 0
F11: =Tabla367891011[[#This Row],[Valor Total]]*19% -> 0 | G11: =Tabla367891011[[#This Row],[Valor Total]]+Tabla367891011[[#This Row],[IVA Incluido]] -> 0
F12: =Tabla367891011[[#This Row],[Valor Total]]*19% -> 0 | G12: =Tabla367891011[[#This Row],[Valor Total]]+Tabla367891011[[#This Row],[IVA Incluido]] -> 0

Sheet Windows Server
A1: Cuadro Comparativo de Cotizaciones
A4: Cotización | B4: Proveedor | C4: URL (Datos de la empresa) | D4: Descripcion | E4: Valor Total | F4: IVA Incluido | G4: Valor Total2 | H4: Forma de Pago | I4: Obsevaciones
A5: Nº1 | B5: REVOLUTION SOFT COLOMBIA | C5: https://revolutionsoft.com.co/windows-server-2022/licencia-windows-server-2022-standard.html?id_product_attribute=0 | D5: Windows Server 2022 Standard | E5: 439000 | I5: Características principales de Windows Server 2022 Standard Seguridad avanzada y protección multicapa Secured-Core Server, integrando medidas de seguridad a nivel de hardware, firmware y software. Protección avanzada contra ataques, con capacidades de cifrado mejoradas y seguridad basada en virtualización (VBS). Windows Defender mejorado, con protección en tiempo real contra amenazas y vulnerabilidades. Rendimiento optimizado y escalabilidad Soporte para 24 cores de procesamiento, garantizando estabilidad y eficiencia en entornos empresariales. Compatibilidad con hasta 2 máquinas virtuales (VMs) y 1 host Hyper-V por licencia. Soporte mejorado para servidores híbridos, facilitando la conexión con Microsoft Azure. Conectividad híbrida y soporte en la nube Azure Arc Integration, permitiendo una administración simplificada desde la nube. SMB over QUIC, mejorando la conectividad remota sin necesidad de usar VPN. Mejoras en contenedores de Windows, optimizando el desarrollo y despliegue de aplicaciones. Compatibilidad y facilidad de gestión Compatibilidad con Active Directory, permitiendo una gestión centralizada de usuarios y dispositivos. Soporte para ReFS (Resilient File System), asegurando mayor protección y eficiencia en el almacenamiento de datos. Windows Admin Center actualizado, con una interfaz mejorada para monitoreo y administración de servidores.
A6: Nº2 | B6: UNIQ | C6: https://uniq.software/es/windows/servers/windows-server-2022/windows-server-2022-standard | D6: Windows Server 2022 Standard | E6: 270000 | I6: Windows Server 2022 Standard cuenta con varias características clave que lo convierten en un sistema operativo de servidor potente y confiable. Algunas de estas características incluyen: Mejora de la seguridad con protección avanzada de varias capas Mejora del rendimiento y la escalabilidad para cargas de trabajo modernas Gestión eficiente de entornos de nube híbrida Soporte para contenerización y arquitectura de microservicios Servicios integrados de Azure para una integración en la nube sin problemas Capacidades avanzadas de almacenamiento con Storage Migration Service y Storage Replica
A7: Nº3
A8: Nº4
F9: =Tabla3678910113[[#This Row],[Valor Total]]*19% -> 0 | G9: =Tabla3678910113[[#This Row],[Valor Total]]+Tabla3678910113[[#This Row],[IVA Incluido]] -> 0
F10: =Tabla3678910113[[#This Row],[Valor Total]]*19% -> 0 | G10: =Tabla3678910113[[#This Row],[Valor Total]]+Tabla3678910113[[#This Row],[IVA Incluido]] -> 0
F11: =Tabla3678910113[[#This Row],[Valor Total]]*19% -> 0 | G11: =Tabla3678910113[[#This Row],[Valor Total]]+Tabla3678910113[[#This Row],[IVA Incluido]] -> 0
F12: =Tabla3678910113[[#This Row],[Valor Total]]*19% -> 0 | G12: =Tabla3678910113[[#This Row],[Valor Total]]+Tabla3678910113[[#This Row],[IVA Incluido]] -> 0

Sheet SoporteTecnico-mantenimiento
A1: Cuadro Comparativo de Cotizaciones
A4: Cotización | B4: Tiempo estimado(Horas) | C4: Valor Unitario (Hora) | D4: Valor Total | E4: Alcance servicio
A5: Soporte Técnico | B5: 20 | C5: 9000 | D5: =Tabla32[[#This Row],[Tiempo estimado(Horas)]]*Tabla32[[#This Row],[Valor Unitario (Hora)]] -> 180000 | E5: -Asistencia en resolución de errores y fallas en el código. - Optimización de rendimiento y seguridad del sistema. - Actualización y mantenimiento de librerías y dependencias. - Documentación técnica de cambios realizados. - Soporte remoto y presencial (según acuerdo).
A6: Actualización del sistema | B6: 40 | C6: 8000 | D6: =Tabla32[[#This Row],[Tiempo estimado(Horas)]]*Tabla32[[#This Row],[Valor Unitario (Hora)]] -> 320000 | E6: - Análisis de la versión actual y diagnóstico de compatibilidad. - Migración de datos y respaldo seguro previo a la actualización. - Instalación de nuevas versiones de módulos y dependencias. - Optimización de rendimiento y seguridad del sistema. - Capacitación básica al personal sobre cambios implementados. - Documentación técnica de la actualización realizada.
A7: Monitoreo del sistema | B7: =8*7*2 -> 112 | C7: 8000 | D7: =Tabla32[[#This Row],[Tiempo estimado(Horas)]]*Tabla32[[#This Row],[Valor Unitario (Hora)]] -> 896000 | E7: - Supervisión en tiempo real del rendimiento del sistema. - Detección temprana de fallas, caídas o anomalías. - Alertas automáticas y reportes periódicos de estado. - Análisis de logs y métricas de seguridad. - Soporte técnico inmediato en caso de incidentes críticos. - Documentación mensual de hallazgos y mejoras recomendadas.
C11: Total | D11: =D5+D6+D7+D8 -> 1396000

Sheet Desarrollo-actividades 
A1: Cuadro Comparativo de Cotizaciones
A4: Cotización | B4: Horas de desarrollo | C4: Valor Unitario (Hora) | D4: Valor Total
A5: BPMN(organización procesos) | B5: 12 | C5: 8000 | D5: =Tabla3212[[#This Row],[Horas de desarrollo]]*Tabla3212[[#This Row],[Valor Unitario (Hora)]] -> 96000
A6: Desarrollo de casos de uso | B6: 60 | C6: 8000 | D6: =Tabla3212[[#This Row],[Horas de desarrollo]]*Tabla3212[[#This Row],[Valor Unitario (Hora)]] -> 480000
A7: Documentación casos de uso | B7: 50 | C7: 8000 | D7: =Tabla3212[[#This Row],[Horas de desarrollo]]*Tabla3212[[#This Row],[Valor Unitario (Hora)]] -> 400000
A8: Mockups(Representación visual proyecto) | B8: 80 | C8: 8000 | D8: =Tabla3212[[#This Row],[Horas de desarrollo]]*Tabla3212[[#This Row],[Valor Unitario (Hora)]] -> 640000
C11: Total | D11: =D5+D6+D7+D8 -> 1616000

Sheet Recursos-Humanos
A1: Cuadro Comparativo de Cotizaciones
A4: Cotización | B4: Responsabilidades | C4: URL (Datos de la empresa ) | D4: Sueldo mensual | E4: IVA Incluido | F4: Valor Total2 | G4: Forma de Pago | H4: Trabajo (Horas) | I4: Costo(Hora) | J4: Costo(Hora)2
A5: Líder de Proyecto | B5: Coordinación del equipo, comunicación con cliente, gestión de tiempos y entregables | C5: https://co.indeed.com/career/l%C3%ADder-de-proyectos/salaries | D5: 3004747 | E5: =Tabla3615[[#This Row],[Sueldo mensual]]*19% -> 570901.93 | F5: =Tabla3615[[#This Row],[Sueldo mensual]]+Tabla3615[[#This Row],[IVA Incluido]] -> 3575648.9 | G5: contado | H5: 40 | I5: =(Tabla3615[[#This Row],[Sueldo mensual]]/30)/8 -> 12519.779 | J5: =Tabla3615[[#This Row],[Costo(Hora)]]*Tabla3615[[#This Row],[Trabajo (Horas)]] -> 500791.17
A6: Desarrollador Frontend | B6: Diseño de interfaces, experiencia de usuario, desarrollo de vistas y formularios | C6: https://co.indeed.com/career/programador-front-end/salaries | D6: 2918813 | E6: =Tabla3615[[#This Row],[Sueldo mensual]]*19% -> 554574.47 | F6: =Tabla3615[[#This Row],[Sueldo mensual]]+Tabla3615[[#This Row],[IVA Incluido]] -> 3473387.5 | G6: contado | H6: 70 | I6: =(Tabla3615[[#This Row],[Sueldo mensual]]/30)/8 -> 12161.721 | J6: =Tabla3615[[#This Row],[Costo(Hora)]]*Tabla3615[[#This Row],[Trabajo (Horas)]] -> 851320.46
A7: Desarrollador Backend | B7: Base de datos, lógica de negocio, APIs, seguridad y autenticación | C7: https://co.indeed.com/career/backend-developer/salaries | D7: 4238411 | E7: =Tabla3615[[#This Row],[Sueldo mensual]]*19% -> 805298.09 | F7: =Tabla3615[[#This Row],[Sueldo mensual]]+Tabla3615[[#This Row],[IVA Incluido]] -> 5043709.1 | G7: contado | H7: 70 | I7: =(Tabla3615[[#This Row],[Sueldo mensual]]/30)/8 -> 17660.046 | J7: =Tabla3615[[#This Row],[Costo(Hora)]]*Tabla3615[[#This Row],[Trabajo (Horas)]] -> 1236203.2
A8: Analista QA / Testing | B8: Pruebas de software, documentación, control de calidad y corrección de errores | C8: https://co.indeed.com/career/analista-qa/salaries | D8: 2998631 | E8: =Tabla3615[[#This Row],[Sueldo mensual]]*19% -> 569739.89 | F8: =Tabla3615[[#This Row],[Sueldo mensual]]+Tabla3615[[#This Row],[IVA Incluido]] -> 3568370.9 | G8: contado | H8: 60 | I8: =(Tabla3615[[#This Row],[Sueldo mensual]]/30)/8 -> 12494.296 | J8: =Tabla3615[[#This Row],[Costo(Hora)]]*Tabla3615[[#This Row],[Trabajo (Horas)]] -> 749657.75
A9: Analista QA / Testing | B9: Pruebas de software, documentación, control de calidad y corrección de errores | C9: https://co.indeed.com/career/analista-qa/salaries | D9: 2998632 | E9: =Tabla3615[[#This Row],[Sueldo mensual]]*19% -> 569740.08 | F9: =Tabla3615[[#This Row],[Sueldo mensual]]+Tabla3615[[#This Row],[IVA Incluido]] -> 3568372.1 | G9: contado | H9: 71 | I9: =(Tabla3615[[#This Row],[Sueldo mensual]]/30)/8 -> 12494.3 | J9: =Tabla3615[[#This Row],[Costo(Hora)]]*Tabla3615[[#This Row],[Trabajo (Horas)]] -> 887095.3
A10: Analista QA / Testing | B10: Pruebas de software, documentación, control de calidad y corrección de errores | C10: https://co.indeed.com/career/analista-qa/salaries | D10: 2998633 | E10: =Tabla3615[[#This Row],[Sueldo mensual]]*19% -> 569740.27 | F10: =Tabla3615[[#This Row],[Sueldo mensual]]+Tabla3615[[#This Row],[IVA Incluido]] -> 3568373.3 | G10: contado | H10: 72 | I10: =(Tabla3615[[#This Row],[Sueldo mensual]]/30)/8 -> 12494.304 | J10: =Tabla3615[[#This Row],[Costo(Hora)]]*Tabla3615[[#This Row],[Trabajo (Horas)]] -> 899589.9
E11: =Tabla3615[[#This Row],[Sueldo mensual]]*19% -> 0 | F11: =Tabla3615[[#This Row],[Sueldo mensual]]+Tabla3615[[#This Row],[IVA Incluido]] -> 0 | G11: contado | I11: Total | J11: =SUM(D5:D8) -> 13160602

Sheet Alquiler-Equipos-Computo
A1: Cuadro Comparativo de Cotizaciones
A4: Cotización | B4: Descripción | C4: URL (Datos del proveedor ) | D4: Costo alquiler(Horas) | E4: IVA Incluido | F4: Valor Total2 | G4: Forma de Pago | H4: Uso Estimado(Horas) | I4: Costo(Hora)2
A5: Líder de Proyecto(Computo) | B5: Coordinación del equipo, comunicación con cliente, gestión de tiempos y entregables | C5: https://www.rentasistemas.com/promocion-portatiles/?gad_source=1&gad_campaignid=22644122367&gbraid=0AAAAADm3cOpC7KPgcwYyO2KCO0R1gRjmi&gclid=Cj0KCQiAiqDJBhCXARIsABk2kSkcN-obVuVAiPLK7ZIuMVjhLfvFV2jxgcbEBxe4gaEUUpqJKX_7OqAaAq6BEALw_wcB | D5: =3728*2 -> 7456 | E5: =Tabla361517[[#This Row],[Costo alquiler(Horas)]]*19% -> 1416.64 | F5: =Tabla361517[[#This Row],[Costo alquiler(Horas)]]+Tabla361517[[#This Row],[IVA Incluido]] -> 8872.64 | G5: contado | H5: 40 | I5: =Tabla361517[[#This Row],[Costo alquiler(Horas)]]*Tabla361517[[#This Row],[Uso Estimado(Horas)]] -> 298240
A6: Desarrollador Frontend(Computo) | B6: Diseño de interfaces, experiencia de usuario, desarrollo de vistas y formularios | C6: https://kcrentas.com.mx/alquiler-de-equipo-de-computo-en-colombia/?gad_source=1&gad_campaignid=21775987673&gbraid=0AAAAAD4oSyN4Kjmpv8B9lH4Efoc4WrWec&gclid=Cj0KCQiAiqDJBhCXARIsABk2kSlTQGeQ0OC0_H3r6xtXj8rAEGFY7YaMCzdBBbRhqrVGSltf6fJ1m7oaAmLYEALw_wcB | D6: =3728*2 -> 7456 | E6: =Tabla361517[[#This Row],[Costo alquiler(Horas)]]*19% -> 1416.64 | F6: =Tabla361517[[#This Row],[Costo alquiler(Horas)]]+Tabla361517[[#This Row],[IVA Incluido]] -> 8872.64 | G6: contado | H6: 70 | I6: =Tabla361517[[#This Row],[Costo alquiler(Horas)]]*Tabla361517[[#This Row],[Uso Estimado(Horas)]] -> 521920
A7: Desarrollador Backend(Computo) | B7: Base de datos, lógica de negocio, APIs, seguridad y autenticación | C7: https://www.rentacomputo.com.co/cuanto-cuesta-alquilar-una-computadora-en-bogota/ | D7: =3728*2.2 -> 8201.6 | E7: =Tabla361517[[#This Row],[Costo alquiler(Horas)]]*19% -> 1558.304 | F7: =Tabla361517[[#This Row],[Costo alquiler(Horas)]]+Tabla361517[[#This Row],[IVA Incluido]] -> 9759.904 | G7: contado | H7: 70 | I7: =Tabla361517[[#This Row],[Costo alquiler(Horas)]]*Tabla361517[[#This Row],[Uso Estimado(Horas)]] -> 574112
A8: Analista QA / Testing(Computo) | B8: Pruebas de software, documentación, control de calidad y corrección de errores | C8: https://lasus.com.co/es/content/renting-alquiler-computadores?srsltid=AfmBOoo10bxgmR3qnJWs-8afuYU8-J22dCcqxYuUFX5iYbg9M9GbXE8_ | D8: =3728*2.2 -> 8201.6 | E8: =Tabla361517[[#This Row],[Costo alquiler(Horas)]]*19% -> 1558.304 | F8: =Tabla361517[[#This Row],[Costo alquiler(Horas)]]+Tabla361517[[#This Row],[IVA Incluido]] -> 9759.904 | G8: contado | H8: 60 | I8: =Tabla361517[[#This Row],[Costo alquiler(Horas)]]*Tabla361517[[#This Row],[Uso Estimado(Horas)]] -> 492096
A9: Analista QA / Testing | B9: Pruebas de software, documentación, control de calidad y corrección de errores | C9: https://co.indeed.com/career/analista-qa/salaries | D9: 2998632 | E9: =Tabla361517[[#This Row],[Costo alquiler(Horas)]]*19% -> 569740.08 | F9: =Tabla361517[[#This Row],[Costo alquiler(Horas)]]+Tabla361517[[#This Row],[IVA Incluido]] -> 3568372.1 | G9: contado | H9: 71 | I9: =#REF!*Tabla361517[[#This Row],[Uso Estimado(Horas)]] -> #REF!
A10: Analista QA / Testing | B10: Pruebas de software, documentación, control de calidad y corrección de errores | C10: https://co.indeed.com/career/analista-qa/salaries | D10: 2998633 | E10: =Tabla361517[[#This Row],[Costo alquiler(Horas)]]*19% -> 569740.27 | F10: =Tabla361517[[#This Row],[Costo alquiler(Horas)]]+Tabla361517[[#This Row],[IVA Incluido]] -> 3568373.3 | G10: contado | H10: 72 | I10: =#REF!*Tabla361517[[#This Row],[Uso Estimado(Horas)]] -> #REF!
E11: =Tabla361517[[#This Row],[Costo alquiler(Horas)]]*19% -> 0 | F11: =Tabla361517[[#This Row],[Costo alquiler(Horas)]]+Tabla361517[[#This Row],[IVA Incluido]] -> 0 | G11: contado | H11: Total | I11: =I5+I6+I7+I8 -> 1886368
E12: =Tabla361517[[#This Row],[Costo alquiler(Horas)]]*19% -> 0 | F12: =Tabla361517[[#This Row],[Costo alquiler(Horas)]]+Tabla361517[[#This Row],[IVA Incluido]] -> 0

Sheet Cotización-final
A1: Cotización final
A4: Concepto | B4: Costo | C4: IVA Incluido | D4: Valor Total2 | E4: Forma de Pago
A5: Recurso Humano (Equipo Desarrollo) | B5: ='Recursos-Humanos'!J11 -> 13160602 | C5: =Tabla361516[[#This Row],[Costo]]*19% -> 2500514.4 | D5: =Tabla361516[[#This Row],[Costo]]+Tabla361516[[#This Row],[IVA Incluido]] -> 15661116 | E5: contado
A6: Desarrollo actividades(entregables) | B6: ='Desarrollo-actividades '!D11 -> 1616000 | C6: =Tabla361516[[#This Row],[Costo]]*19% -> 307040 | D6: =Tabla361516[[#This Row],[Costo]]+Tabla361516[[#This Row],[IVA Incluido]] -> 1923040 | E6: contado
A7: Soporte Tecnico y mantenimiento | B7: ='SoporteTecnico-mantenimiento'!D11 -> 1396000 | C7: =Tabla361516[[#This Row],[Costo]]*19% -> 265240 | D7: =Tabla361516[[#This Row],[Costo]]+Tabla361516[[#This Row],[IVA Incluido]] -> 1661240 | E7: contado
A8: Alquiler equipos computo | B8: ='Alquiler-Equipos-Computo'!I11 -> 1886368 | C8: =Tabla361516[[#This Row],[Costo]]*19% -> 358409.92 | D8: =Tabla361516[[#This Row],[Costo]]+Tabla361516[[#This Row],[IVA Incluido]] -> 2244777.9 | E8: contado
A9: Analista QA / Testing | B9: 2998631 | C9: =Tabla361516[[#This Row],[Costo]]*19% -> 569739.89 | D9: =Tabla361516[[#This Row],[Costo]]+Tabla361516[[#This Row],[IVA Incluido]] -> 3568370.9 | E9: contado
A10: Analista QA / Testing | B10: 2998631 | C10: =Tabla361516[[#This Row],[Costo]]*19% -> 569739.89 | D10: =Tabla361516[[#This Row],[Costo]]+Tabla361516[[#This Row],[IVA Incluido]] -> 3568370.9 | E10: contado
A11: Dominio | B11: =Dominio!E5 -> 57000 | C11: =Tabla361516[[#This Row],[Costo]]*19% -> 10830 | D11: =Tabla361516[[#This Row],[Costo]]+Tabla361516[[#This Row],[IVA Incluido]] -> 67830 | E11: contado
A12: Hosting - Servidor web | B12: ='Hosting-Servidor-web'!E5 -> 169900 | C12: =Tabla361516[[#This Row],[Costo]]*19% -> 32281 | D12: =Tabla361516[[#This Row],[Costo]]+Tabla361516[[#This Row],[IVA Incluido]] -> 202181 | E12: contado
A13: Servidor físico | B13: 4200000 | C13: =Tabla361516[[#This Row],[Costo]]*19% -> 798000 | D13: =Tabla361516[[#This Row],[Costo]]+Tabla361516[[#This Row],[IVA Incluido]] -> 4998000 | E13: contado
A14: Licencia | B14: ='Licencias de Windows'!E6 -> 39900 | C14: =Tabla361516[[#This Row],[Costo]]*19% -> 7581 | D14: =Tabla361516[[#This Row],[Costo]]+Tabla361516[[#This Row],[IVA Incluido]] -> 47481 | E14: contado
A15: Bases de datos | B15: ='Base de Datos'!E5 -> 1790000 | C15: =Tabla361516[[#This Row],[Costo]]*19% -> 340100 | D15: =Tabla361516[[#This Row],[Costo]]+Tabla361516[[#This Row],[IVA Incluido]] -> 2130100 | E15: contado
A16: Windows server | B16: ='Windows Server'!E6 -> 270000 | C16: =Tabla361516[[#This Row],[Costo]]*19% -> 51300 | D16: =Tabla361516[[#This Row],[Costo]]+Tabla361516[[#This Row],[IVA Incluido]] -> 321300 | E16: contado
A17: Visual estudio | B17: ='Visual Studio'!E5 -> 99000 | C17: =Tabla361516[[#This Row],[Costo]]*19% -> 18810 | D17: =Tabla361516[[#This Row],[Costo]]+Tabla361516[[#This Row],[IVA Incluido]] -> 117810 | E17: contado
A18: Total | B18: =SUM(B5:B17) -> 30682032 | C18: =Tabla361516[[#This Row],[Costo]]*19% -> 5829586.1 | D18: =Tabla361516[[#This Row],[Costo]]+Tabla361516[[#This Row],[IVA Incluido]] -> 36511618 | E18: contado
